lava/lib/optimization/README.md
lava/lib/optimization/apps/clustering/problems.py
lava/lib/optimization/apps/clustering/solver.py
lava/lib/optimization/apps/clustering/utils/q_matrix_generator.py
lava/lib/optimization/apps/scheduler/problems.py
lava/lib/optimization/apps/scheduler/solver.py
lava/lib/optimization/apps/tsp/problems.py
lava/lib/optimization/apps/tsp/solver.py
lava/lib/optimization/apps/tsp/utils/q_matrix_generator.py
lava/lib/optimization/problems/bayesian/models.py
lava/lib/optimization/problems/bayesian/processes.py
lava/lib/optimization/problems/coefficients.py
lava/lib/optimization/problems/constraints.py
lava/lib/optimization/problems/cost.py
lava/lib/optimization/problems/problems.py
lava/lib/optimization/problems/variables.py
lava/lib/optimization/solvers/bayesian/models.py
lava/lib/optimization/solvers/bayesian/processes.py
lava/lib/optimization/solvers/bayesian/solver.py
lava/lib/optimization/solvers/generic/annealing/process.py
lava/lib/optimization/solvers/generic/builder.py
lava/lib/optimization/solvers/generic/cost_integrator/models.py
lava/lib/optimization/solvers/generic/cost_integrator/process.py
lava/lib/optimization/solvers/generic/dataclasses.py
lava/lib/optimization/solvers/generic/hierarchical_processes.py
lava/lib/optimization/solvers/generic/monitoring_processes/solution_readout/models.py
lava/lib/optimization/solvers/generic/monitoring_processes/solution_readout/process.py
lava/lib/optimization/solvers/generic/nebm/models.py
lava/lib/optimization/solvers/generic/nebm/process.py
lava/lib/optimization/solvers/generic/processes.py
lava/lib/optimization/solvers/generic/qp/models.py
lava/lib/optimization/solvers/generic/qp/processes.py
lava/lib/optimization/solvers/generic/qp/solver.py
lava/lib/optimization/solvers/generic/read_gate/models.py
lava/lib/optimization/solvers/generic/read_gate/process.py
lava/lib/optimization/solvers/generic/scif/models.py
lava/lib/optimization/solvers/generic/scif/process.py
lava_optimization-0.5.0.dist-info/LICENSE
lava_optimization-0.5.0.dist-info/METADATA
lava_optimization-0.5.0.dist-info/WHEEL
lava_optimization-0.5.0.dist-info/RECORD
